{
  "generation": 1,
  "group_id": null,
  "strategy": "add_new_spec",
  "feedback": {
    "cohesion": "No cohesion feedback available",
    "coverage": "No coverage feedback available",
    "redundancy": "No redundancy feedback available",
    "practicality": "No practicality feedback available"
  },
  "similar_specs_count": 2,
  "selected_specs": [
    {
      "id": "ae69357915db",
      "score": 76,
      "elo": 1507.0061858295314,
      "text": "MUST verify insurance product information against current carrier offerings and regulatory filings before providing coverage comparisons or recommendations."
    },
    {
      "id": "b3c6a1c0b06b",
      "score": 55,
      "elo": 1501.8729102946038,
      "text": "MUST detect insurance coverage adequacy questions and transform responses into educational content about insurance types and coverage evaluation principles."
    }
  ]
}